{
    "description": "TYPE: CUSTOM\nMaterial Theme Builder export 2025-12-25 08:39:02",
    "seed": "#FF1744",
    "coreColors": {
        "primary": "#FF1744"
    },
    "extendedColors": [],
    "schemes": {
        "light": {
            "primary": "#BA002C",
            "surfaceTint": "#BF002E",
            "onPrimary": "#FFFFFF",
            "primaryContainer": "#E9003A",
            "onPrimaryContainer": "#FFFBFF",
            "secondary": "#B12937",
            "onSecondary": "#FFFFFF",
            "secondaryContainer": "#FD616A",
            "onSecondaryContainer": "#640013",
            "tertiary": "#934700",
            "onTertiary": "#FFFFFF",
            "tertiaryContainer": "#B85A00",
            "onTertiaryContainer": "#FFFBFF",
            "error": "#BA1A1A",
            "onError": "#FFFFFF",
            "errorContainer": "#FFDAD6",
            "onErrorContainer": "#93000A",
            "background": "#FFF8F7",
            "onBackground": "#291616",
            "surface": "#FFF8F7",
            "onSurface": "#291616",
            "surfaceVariant": "#FFDAD9",
            "onSurfaceVariant": "#5E3F3E",
            "outline": "#936E6D",
            "outlineVariant": "#E8BCBB",
            "shadow": "#000000",
            "scrim": "#000000",
            "inverseSurface": "#412B2B",
            "inverseOnSurface": "#FFEDEC",
            "inversePrimary": "#FFB3B3",
            "primaryFixed": "#FFDAD9",
            "onPrimaryFixed": "#400009",
            "primaryFixedDim": "#FFB3B3",
            "onPrimaryFixedVariant": "#920021",
            "secondaryFixed": "#FFDAD9",
            "onSecondaryFixed": "#400009",
            "secondaryFixedDim": "#FFB3B3",
            "onSecondaryFixedVariant": "#900A23",
            "tertiaryFixed": "#FFDBC7",
            "onTertiaryFixed": "#311300",
            "tertiaryFixedDim": "#FFB688",
            "onTertiaryFixedVariant": "#733600",
            "surfaceDim": "#F5D2D1",
            "surfaceBright": "#FFF8F7",
            "surfaceContainerLowest": "#FFFFFF",
            "surfaceContainerLow": "#FFF0EF",
            "surfaceContainer": "#FFE9E8",
            "surfaceContainerHigh": "#FFE1E0",
            "surfaceContainerHighest": "#FEDAD9"
        },
        "light-medium-contrast": {
            "primary": "#730017",
            "surfaceTint": "#BF002E",
            "onPrimary": "#FFFFFF",
            "primaryContainer": "#DB0036",
            "onPrimaryContainer": "#FFFFFF",
            "secondary": "#730017",
            "onSecondary": "#FFFFFF",
            "secondaryContainer": "#C63845",
            "onSecondaryContainer": "#FFFFFF",
            "tertiary": "#592800",
            "onTertiary": "#FFFFFF",
            "tertiaryContainer": "#AD5400",
            "onTertiaryContainer": "#FFFFFF",
            "error": "#740006",
            "onError": "#FFFFFF",
            "errorContainer": "#CF2C27",
            "onErrorContainer": "#FFFFFF",
            "background": "#FFF8F7",
            "onBackground": "#291616",
            "surface": "#FFF8F7",
            "onSurface": "#1E0C0C",
            "surfaceVariant": "#FFDAD9",
            "onSurfaceVariant": "#4B2E2E",
            "outline": "#6B4A4A",
            "outlineVariant": "#886464",
            "shadow": "#000000",
            "scrim": "#000000",
            "inverseSurface": "#412B2B",
            "inverseOnSurface": "#FFEDEC",
            "inversePrimary": "#FFB3B3",
            "primaryFixed": "#DB0036",
            "onPrimaryFixed": "#FFFFFF",
            "primaryFixedDim": "#AD0028",
            "onPrimaryFixedVariant": "#FFFFFF",
            "secondaryFixed": "#C63845",
            "onSecondaryFixed": "#FFFFFF",
            "secondaryFixedDim": "#A41E2F",
            "onSecondaryFixedVariant": "#FFFFFF",
            "tertiaryFixed": "#AD5400",
            "onTertiaryFixed": "#FFFFFF",
            "tertiaryFixedDim": "#884100",
            "onTertiaryFixedVariant": "#FFFFFF",
            "surfaceDim": "#E1BEBE",
            "surfaceBright": "#FFF8F7",
            "surfaceContainerLowest": "#FFFFFF",
            "surfaceContainerLow": "#FFF0EF",
            "surfaceContainer": "#FFE1E0",
            "surfaceContainerHigh": "#F8D5D4",
            "surfaceContainerHighest": "#ECC9C9"
        },
        "light-high-contrast": {
            "primary": "#600012",
            "surfaceTint": "#BF002E",
            "onPrimary": "#FFFFFF",
            "primaryContainer": "#970022",
            "onPrimaryContainer": "#FFFFFF",
            "secondary": "#600012",
            "onSecondary": "#FFFFFF",
            "secondaryContainer": "#930E25",
            "onSecondaryContainer": "#FFFFFF",
            "tertiary": "#4A2000",
            "onTertiary": "#FFFFFF",
            "tertiaryContainer": "#763800",
            "onTertiaryContainer": "#FFFFFF",
            "error": "#600004",
            "onError": "#FFFFFF",
            "errorContainer": "#98000A",
            "onErrorContainer": "#FFFFFF",
            "background": "#FFF8F7",
            "onBackground": "#291616",
            "surface": "#FFF8F7",
            "onSurface": "#000000",
            "surfaceVariant": "#FFDAD9",
            "onSurfaceVariant": "#000000",
            "outline": "#402525",
            "outlineVariant": "#614141",
            "shadow": "#000000",
            "scrim": "#000000",
            "inverseSurface": "#412B2B",
            "inverseOnSurface": "#FFFFFF",
            "inversePrimary": "#FFB3B3",
            "primaryFixed": "#970022",
            "onPrimaryFixed": "#FFFFFF",
            "primaryFixedDim": "#6C0015",
            "onPrimaryFixedVariant": "#FFFFFF",
            "secondaryFixed": "#930E25",
            "onSecondaryFixed": "#FFFFFF",
            "secondaryFixedDim": "#6C0015",
            "onSecondaryFixedVariant": "#FFFFFF",
            "tertiaryFixed": "#763800",
            "onTertiaryFixed": "#FFFFFF",
            "tertiaryFixedDim": "#542600",
            "onTertiaryFixedVariant": "#FFFFFF",
            "surfaceDim": "#D2B1B0",
            "surfaceBright": "#FFF8F7",
            "surfaceContainerLowest": "#FFFFFF",
            "surfaceContainerLow": "#FFEDEC",
            "surfaceContainer": "#FEDAD9",
            "surfaceContainerHigh": "#EFCCCB",
            "surfaceContainerHighest": "#E1BEBE"
        },
        "dark": {
            "primary": "#FFB3B3",
            "surfaceTint": "#FFB3B3",
            "onPrimary": "#680014",
            "primaryContainer": "#FF525F",
            "onPrimaryContainer": "#3D0008",
            "secondary": "#FFB3B3",
            "onSecondary": "#680014",
            "secondaryContainer": "#900A23",
            "onSecondaryContainer": "#FF989A",
            "tertiary": "#FFB688",
            "onTertiary": "#512400",
            "tertiaryContainer": "#E07316",
            "onTertiaryContainer": "#2E1200",
            "error": "#FFB4AB",
            "onError": "#690005",
            "errorContainer": "#93000A",
            "onErrorContainer": "#FFDAD6",
            "background": "#200E0F",
            "onBackground": "#FEDAD9",
            "surface": "#200E0F",
            "onSurface": "#FEDAD9",
            "surfaceVariant": "#5E3F3E",
            "onSurfaceVariant": "#E8BCBB",
            "outline": "#AE8787",
            "outlineVariant": "#5E3F3E",
            "shadow": "#000000",
            "scrim": "#000000",
            "inverseSurface": "#FEDAD9",
            "inverseOnSurface": "#412B2B",
            "inversePrimary": "#BF002E",
            "primaryFixed": "#FFDAD9",
            "onPrimaryFixed": "#400009",
            "primaryFixedDim": "#FFB3B3",
            "onPrimaryFixedVariant": "#920021",
            "secondaryFixed": "#FFDAD9",
            "onSecondaryFixed": "#400009",
            "secondaryFixedDim": "#FFB3B3",
            "onSecondaryFixedVariant": "#900A23",
            "tertiaryFixed": "#FFDBC7",
            "onTertiaryFixed": "#311300",
            "tertiaryFixedDim": "#FFB688",
            "onTertiaryFixedVariant": "#733600",
            "surfaceDim": "#200E0F",
            "surfaceBright": "#4A3333",
            "surfaceContainerLowest": "#1A090A",
            "surfaceContainerLow": "#291616",
            "surfaceContainer": "#2E1A1A",
            "surfaceContainerHigh": "#3A2424",
            "surfaceContainerHighest": "#452F2F"
        },
        "dark-medium-contrast": {
            "primary": "#FFD1D1",
            "surfaceTint": "#FFB3B3",
            "onPrimary": "#54000E",
            "primaryContainer": "#FF525F",
            "onPrimaryContainer": "#000000",
            "secondary": "#FFD1D1",
            "onSecondary": "#54000E",
            "secondaryContainer": "#F65C65",
            "onSecondaryContainer": "#000000",
            "tertiary": "#FFD4BA",
            "onTertiary": "#401B00",
            "tertiaryContainer": "#E07316",
            "onTertiaryContainer": "#000000",
            "error": "#FFD2CC",
            "onError": "#540003",
            "errorContainer": "#FF5449",
            "onErrorContainer": "#000000",
            "background": "#200E0F",
            "onBackground": "#FEDAD9",
            "surface": "#200E0F",
            "onSurface": "#FFFFFF",
            "surfaceVariant": "#5E3F3E",
            "onSurfaceVariant": "#FFD1D1",
            "outline": "#D2A8A7",
            "outlineVariant": "#AE8786",
            "shadow": "#000000",
            "scrim": "#000000",
            "inverseSurface": "#FEDAD9",
            "inverseOnSurface": "#3A2424",
            "inversePrimary": "#940021",
            "primaryFixed": "#FFDAD9",
            "onPrimaryFixed": "#2D0004",
            "primaryFixedDim": "#FFB3B3",
            "onPrimaryFixedVariant": "#730017",
            "secondaryFixed": "#FFDAD9",
            "onSecondaryFixed": "#2D0004",
            "secondaryFixedDim": "#FFB3B3",
            "onSecondaryFixedVariant": "#730017",
            "tertiaryFixed": "#FFDBC7",
            "onTertiaryFixed": "#210B00",
            "tertiaryFixedDim": "#FFB688",
            "onTertiaryFixedVariant": "#592800",
            "surfaceDim": "#200E0F",
            "surfaceBright": "#563E3E",
            "surfaceContainerLowest": "#120404",
            "surfaceContainerLow": "#2C1818",
            "surfaceContainer": "#372222",
            "surfaceContainerHigh": "#432D2D",
            "surfaceContainerHighest": "#4F3838"
        },
        "dark-high-contrast": {
            "primary": "#FFECEB",
            "surfaceTint": "#FFB3B3",
            "onPrimary": "#000000",
            "primaryContainer": "#FFADAD",
            "onPrimaryContainer": "#220003",
            "secondary": "#FFECEB",
            "onSecondary": "#000000",
            "secondaryContainer": "#FFADAD",
            "onSecondaryContainer": "#220003",
            "tertiary": "#FFECE3",
            "onTertiary": "#000000",
            "tertiaryContainer": "#FFB17E",
            "onTertiaryContainer": "#180700",
            "error": "#FFECE9",
            "onError": "#000000",
            "errorContainer": "#FFAEA4",
            "onErrorContainer": "#220001",
            "background": "#200E0F",
            "onBackground": "#FEDAD9",
            "surface": "#200E0F",
            "onSurface": "#FFFFFF",
            "surfaceVariant": "#5E3F3E",
            "onSurfaceVariant": "#FFFFFF",
            "outline": "#FFECEB",
            "outlineVariant": "#E4B8B7",
            "shadow": "#000000",
            "scrim": "#000000",
            "inverseSurface": "#FEDAD9",
            "inverseOnSurface": "#000000",
            "inversePrimary": "#940021",
            "primaryFixed": "#FFDAD9",
            "onPrimaryFixed": "#000000",
            "primaryFixedDim": "#FFB3B3",
            "onPrimaryFixedVariant": "#2D0004",
            "secondaryFixed": "#FFDAD9",
            "onSecondaryFixed": "#000000",
            "secondaryFixedDim": "#FFB3B3",
            "onSecondaryFixedVariant": "#2D0004",
            "tertiaryFixed": "#FFDBC7",
            "onTertiaryFixed": "#000000",
            "tertiaryFixedDim": "#FFB688",
            "onTertiaryFixedVariant": "#210B00",
            "surfaceDim": "#200E0F",
            "surfaceBright": "#634A4A",
            "surfaceContainerLowest": "#000000",
            "surfaceContainerLow": "#2E1A1A",
            "surfaceContainer": "#412B2B",
            "surfaceContainerHigh": "#4D3635",
            "surfaceContainerHighest": "#594140"
        }
    },
    "palettes": {
        "primary": {
            "0": "#000000",
            "5": "#2C0004",
            "10": "#400009",
            "15": "#54000E",
            "20": "#680014",
            "25": "#7D001A",
            "30": "#920021",
            "35": "#A80027",
            "40": "#BF002E",
            "50": "#EE003B",
            "60": "#FF525F",
            "70": "#FF888B",
            "80": "#FFB3B3",
            "90": "#FFDAD9",
            "95": "#FFEDEC",
            "98": "#FFF8F7",
            "99": "#FFFBFF",
            "100": "#FFFFFF"
        },
        "secondary": {
            "0": "#000000",
            "5": "#2B0105",
            "10": "#3A090E",
            "15": "#481417",
            "20": "#551E21",
            "25": "#63292B",
            "30": "#713436",
            "35": "#803F41",
            "40": "#8E4B4C",
            "50": "#AB6363",
            "60": "#C97B7C",
            "70": "#E79595",
            "80": "#FFB3B3",
            "90": "#FFDAD9",
            "95": "#FFEDEC",
            "98": "#FFF8F7",
            "99": "#FFFBFF",
            "100": "#FFFFFF"
        },
        "tertiary": {
            "0": "#000000",
            "5": "#1A0F00",
            "10": "#281900",
            "15": "#352200",
            "20": "#432C00",
            "25": "#523600",
            "30": "#604100",
            "35": "#704B00",
            "40": "#7F5600",
            "50": "#9F6D00",
            "60": "#C18500",
            "70": "#E09F20",
            "80": "#FFBA3F",
            "90": "#FFDEAE",
            "95": "#FFEEDA",
            "98": "#FFF8F3",
            "99": "#FFFBFF",
            "100": "#FFFFFF"
        },
        "neutral": {
            "0": "#000000",
            "5": "#15100F",
            "10": "#201A1A",
            "15": "#2B2424",
            "20": "#362F2E",
            "25": "#413A39",
            "30": "#4D4545",
            "35": "#595050",
            "40": "#655C5C",
            "50": "#7F7574",
            "60": "#998E8E",
            "70": "#B4A9A8",
            "80": "#D0C4C3",
            "90": "#ECE0DF",
            "95": "#FBEEED",
            "98": "#FFF8F7",
            "99": "#FFFBFF",
            "100": "#FFFFFF"
        },
        "neutral-variant": {
            "0": "#000000",
            "5": "#190E0E",
            "10": "#251818",
            "15": "#302322",
            "20": "#3B2D2D",
            "25": "#463838",
            "30": "#524343",
            "35": "#5F4F4E",
            "40": "#6B5A5A",
            "50": "#857372",
            "60": "#A08C8C",
            "70": "#BBA6A6",
            "80": "#D7C1C1",
            "90": "#F4DDDC",
            "95": "#FFEDEC",
            "98": "#FFF8F7",
            "99": "#FFFBFF",
            "100": "#FFFFFF"
        }
    }
}